motpy/__init__.py
motpy/core.py
motpy/detector.py
motpy/metrics.py
motpy/model.py
motpy/testing.py
motpy/testing_viz.py
motpy/tracker.py
motpy/utils.py
motpy-0.0.10.dist-info/LICENSE
motpy-0.0.10.dist-info/METADATA
motpy-0.0.10.dist-info/WHEEL
motpy-0.0.10.dist-info/top_level.txt
motpy-0.0.10.dist-info/RECORD
