Metadata-Version: 2.1
Name: motpy
Version: 0.0.10
Summary: Library for track-by-detection multi object tracking implemented in python
Home-page: https://github.com/wmuron/motpy.git
Author: Wiktor Muron
Author-email: wiktormuron@gmail.com
License: MIT
Download-URL: https://github.com/wmuron/motpy/releases/tag/v0.0.10-alpha
Keywords: multi-object-tracking,object-tracking,kalman-filter
Platform: UNKNOWN
Classifier: Development Status :: 3 - Alpha
Classifier: Intended Audience :: Developers
Classifier: Topic :: Software Development :: Libraries :: Python Modules
Classifier: License :: OSI Approved :: MIT License
Requires-Python: >3.6
License-File: LICENSE
Requires-Dist: numpy
Requires-Dist: scipy
Requires-Dist: filterpy
